svneverever/__init__.py
svneverever/__main__.py
svneverever/version.py
svneverever-1.7.2.dist-info/METADATA
svneverever-1.7.2.dist-info/WHEEL
svneverever-1.7.2.dist-info/entry_points.txt
svneverever-1.7.2.dist-info/top_level.txt
svneverever-1.7.2.dist-info/RECORD
