Metadata-Version: 2.1
Name: svneverever
Version: 1.7.2
Summary: Tool collecting path entries across SVN history
Home-page: https://github.com/hartwork/svneverever
Author: Sebastian Pipping
Author-email: sebastian@pipping.org
License: GPL v3 or later
Classifier: Development Status :: 5 - Production/Stable
Classifier: Environment :: Console
Classifier: Intended Audience :: Developers
Classifier: Intended Audience :: System Administrators
Classifier: License :: OSI Approved :: GNU General Public License v3 or later (GPLv3+)
Classifier: Natural Language :: English
Classifier: Programming Language :: Python
Classifier: Programming Language :: Python :: 3
Classifier: Programming Language :: Python :: 3.7
Classifier: Programming Language :: Python :: 3.8
Classifier: Programming Language :: Python :: 3 :: Only
Classifier: Topic :: Software Development :: Version Control
Classifier: Topic :: Utilities
Requires-Python: >=3.7
